fhermocunha2025_meu_primeiro_pacote-0.0.1.dist-info/licenses/LICENSE.txt
meu_primeiro_pacote/__init__.py
meu_primeiro_pacote/modulo1.py
meu_primeiro_pacote/modulo2.py
fhermocunha2025_meu_primeiro_pacote-0.0.1.dist-info/METADATA
fhermocunha2025_meu_primeiro_pacote-0.0.1.dist-info/WHEEL
fhermocunha2025_meu_primeiro_pacote-0.0.1.dist-info/top_level.txt
fhermocunha2025_meu_primeiro_pacote-0.0.1.dist-info/RECORD
