Metadata-Version: 2.4
Name: fhermocunha2025-meu_primeiro_pacote
Version: 0.0.1
Summary: Um pacote Python simples para demonstração
Home-page: https://github.com/fhermocunha2025/meu_primeiro_pacote
Author: Seu Nome
Author-email: seu_email@exemplo.com
Classifier: Programming Language :: Python :: 3
Classifier: License :: OSI Approved :: MIT License
Classifier: Operating System :: OS Independent
Requires-Python: >=3.6
License-File: LICENSE.txt
Dynamic: author
Dynamic: author-email
Dynamic: classifier
Dynamic: description
Dynamic: description-content-type
Dynamic: home-page
Dynamic: license-file
Dynamic: requires-python
Dynamic: summary
